{
  "version": 1,
  "original_file_name": "checkpoints_v2.zip",
  "original_size": 122185781,
  "original_sha256": "519d8a48ebc7d20483b238646fa5990b998181ddc5c35e842c130d4fca840f66",
  "num_chunks_requested": 5,
  "num_chunks_written": 5,
  "chunks": [
    {
      "index": 0,
      "file": "checkpoints_v2.zip.part0000",
      "size": 24437157,
      "offset": 0,
      "sha256": "6dbb1327f7e2fcb0088733b55d5b4f36611f5a3e80bd3af33d81684dbf631824"
    },
    {
      "index": 1,
      "file": "checkpoints_v2.zip.part0001",
      "size": 24437157,
      "offset": 24437157,
      "sha256": "6514af84ad820028186a989f431e3d76b61a17f2c7a16fd8a85aeb7914cc9def"
    },
    {
      "index": 2,
      "file": "checkpoints_v2.zip.part0002",
      "size": 24437157,
      "offset": 48874314,
      "sha256": "439d06eaf8cabea05d9d150d0d72d0d3b223e71c14a5bfc5cc16a37a0960da59"
    },
    {
      "index": 3,
      "file": "checkpoints_v2.zip.part0003",
      "size": 24437157,
      "offset": 73311471,
      "sha256": "f4c9c0c981fe810e3da214ca5c3e6f8e14fb913cdce08e61a8411aa3c9e3f7e0"
    },
    {
      "index": 4,
      "file": "checkpoints_v2.zip.part0004",
      "size": 24437153,
      "offset": 97748628,
      "sha256": "1ee0f4c59165ccfa53426f56da0cf5351c44437684dd0472dd04be394838bae1"
    }
  ]
}
